[
  {
    "member_id": 1,
    "nama": "Rich Brian",
    "email": "brian@example.com",
    "tipe_member": "gold"
  },
  {
    "member_id": 2,
    "nama": "Rizky Pratama",
    "email": "pratama@example.com",
    "tipe_member": "silver"
  },
  {
    "member_id": 3,
    "nama": "Bambang Pacul",
    "email": "bambang@example.com",
    "tipe_member": "platinum"
  },
  {
    "member_id": 4,
    "nama": "Agus Salim",
    "email": "salim@example.com",
    "tipe_member": "silver"
  },
  {
    "member_id": 5,
    "nama": "Melati Putri",
    "email": "melati@example.com",
    "tipe_member": "gold"
  }
]
